deephaven_altair/__init__.py
deephaven_altair/deephaven_altair_type.py
deephaven_altair/js_plugin.py
deephaven_altair/register.py
deephaven_altair/_js/package.json
deephaven_altair/_js/dist/index.js
deephaven_altair-0.0.1.dist-info/LICENSE
deephaven_altair-0.0.1.dist-info/METADATA
deephaven_altair-0.0.1.dist-info/WHEEL
deephaven_altair-0.0.1.dist-info/entry_points.txt
deephaven_altair-0.0.1.dist-info/top_level.txt
deephaven_altair-0.0.1.dist-info/RECORD
