Metadata-Version: 2.1
Name: deephaven_altair
Version: 0.0.1
Summary: plugin for deephaven
Author: Joe Numainville
Author-email: josephnumainville@deephaven.io
Keywords: deephaven,plugin,graph
Platform: any
License-File: LICENSE
Requires-Dist: deephaven-core >=0.31.0
Requires-Dist: deephaven-plugin >=0.6.0
Requires-Dist: deephaven-plugin-utilities
Requires-Dist: altair
